setup.py
usercontrol/__init__.py
usercontrol/alldo.py
usercontrol.egg-info/PKG-INFO
usercontrol.egg-info/SOURCES.txt
usercontrol.egg-info/dependency_links.txt
usercontrol.egg-info/top_level.txt