Metadata-Version: 1.1
Name: usercontrol
Version: 0.0.1
Summary: 里面有很多的用户操作函数，快来试试吧！
Home-page: https://github.com/
Author: Yanming Guo
Author-email: gyms1111@163.com
License: UNKNOWN
Platform: UNKNOWN
Classifier: Programming Language :: Python :: 3
Classifier: License :: OSI Approved :: MIT License
Classifier: Operating System :: OS Independent
